odata/__init__.py
odata/accumulationregister.py
odata/catalog.py
odata/core.py
odata/document.py
odata/informationregister.py
odata/postingmode.py
python_1c_odata-0.1.2.dist-info/licenses/LICENSE
python_1c_odata-0.1.2.dist-info/METADATA
python_1c_odata-0.1.2.dist-info/WHEEL
python_1c_odata-0.1.2.dist-info/top_level.txt
python_1c_odata-0.1.2.dist-info/RECORD
