Metadata-Version: 2.4
Name: python-1c-odata
Version: 0.1.2
Summary: Библиотека для работы с 1С через OData
Home-page: https://github.com/itsuppartem/python-1c-odata
Author: Artem Guliaev
Author-email: itsuppartem@yandex.ri
Classifier: Programming Language :: Python :: 3
Classifier: License :: OSI Approved :: MIT License
Classifier: Operating System :: OS Independent
Requires-Python: >=3.7
License-File: LICENSE
Requires-Dist: aiohttp>=3.8.0
Dynamic: author
Dynamic: author-email
Dynamic: classifier
Dynamic: description
Dynamic: description-content-type
Dynamic: home-page
Dynamic: license-file
Dynamic: requires-dist
Dynamic: requires-python
Dynamic: summary
